risksutils/__init__.py
risksutils/metrics.py
risksutils/models.py
risksutils/visualization.py
risksutils-0.1.16.dist-info/LICENSE
risksutils-0.1.16.dist-info/METADATA
risksutils-0.1.16.dist-info/WHEEL
risksutils-0.1.16.dist-info/top_level.txt
risksutils-0.1.16.dist-info/RECORD
