Metadata-Version: 2.1
Name: risksutils
Version: 0.1.16
Summary: Scripts for credit scoring analysis
Home-page: https://github.com/dshulchevskii/risksutils
Author: Dmitry Shulchevskii
Author-email: dshulchevskii@gmail.com
License: MIT
Keywords: woe credit scoring information-value visualization
Platform: UNKNOWN
Classifier: Development Status :: 3 - Alpha
Classifier: Intended Audience :: Financial and Insurance Industry
Classifier: License :: OSI Approved :: MIT License
Classifier: Programming Language :: Python :: 3.6
Requires-Dist: pandas (>=0.22.0)
Requires-Dist: holoviews (>=1.9.0)
Requires-Dist: numpy (>=1.13.1)
Requires-Dist: scikit-learn (>=0.19.0)
Requires-Dist: scipy (>=0.19.1)
Requires-Dist: matplotlib (>=2.0.2)
Requires-Dist: bokeh (>=0.12.10)
Requires-Dist: statsmodels (>=0.8.0)
